wagtail_synopsis/__init__.py
wagtail_synopsis/admin_urls.py
wagtail_synopsis/apps.py
wagtail_synopsis/auxiliaries.py
wagtail_synopsis/blocks.py
wagtail_synopsis/content_admin.py
wagtail_synopsis/curation.py
wagtail_synopsis/default_settings.py
wagtail_synopsis/fields.py
wagtail_synopsis/form_fields.py
wagtail_synopsis/mixins.py
wagtail_synopsis/model_porter.py
wagtail_synopsis/models.py
wagtail_synopsis/urls.py
wagtail_synopsis/validators.py
wagtail_synopsis/wagtail_hooks.py
wagtail_synopsis/migrations/0001_initial.py
wagtail_synopsis/migrations/__init__.py
wagtail_synopsis/templates/wagtail_synopsis/blocks/synopsis_list.html
wagtail_synopsis/templates/wagtail_synopsis/blocks/textual_synopsis.html
wagtail_synopsis/templates/wagtail_synopsis/blocks/visual_synopsis.html
wagtail_synopsis/templates/wagtail_synopsis/blocks/visual_synopsis_switch.html
wagtail_synopsis/templates/wagtail_synopsis/tags/support.html
wagtail_synopsis/templatetags/__init__.py
wagtail_synopsis/templatetags/wagtail_synopsis_tags.py
wagtail_synopsis-4.1.0.dist-info/AUTHORS.txt
wagtail_synopsis-4.1.0.dist-info/LICENSE.txt
wagtail_synopsis-4.1.0.dist-info/METADATA
wagtail_synopsis-4.1.0.dist-info/WHEEL
wagtail_synopsis-4.1.0.dist-info/top_level.txt
wagtail_synopsis-4.1.0.dist-info/RECORD
